misprimos/primo.py
misprimos-1.0.dist-info/LICENSE
misprimos-1.0.dist-info/METADATA
misprimos-1.0.dist-info/WHEEL
misprimos-1.0.dist-info/top_level.txt
misprimos-1.0.dist-info/RECORD
