Metadata-Version: 2.1
Name: misprimos
Version: 1.0
Summary: A tool to calculate prime number.
Home-page: UNKNOWN
Author: Juan Camilo Amaya
Author-email: webjcaf022014@gmail.com
License: GNU GPLv3
Keywords: pyoperaciones mathematical operations
Platform: UNKNOWN
Classifier: Development Status :: 4 - Beta
Classifier: Intended Audience :: Developers
Classifier: Topic :: Utilities
Classifier: License :: OSI Approved :: GNU General Public License v3 (GPLv3)
Classifier: Programming Language :: Python :: 3
Classifier: Operating System :: OS Independent
License-File: LICENSE
